{
	"sprite": "spr_font_fish",
	"mono": false,
	"base_height": 7,
	"space_x": 1,
	"space_y": 2,
	"tab_size": 6,
	"space_invalid": 4,
	
	"chars": {
		"0": {
			"h": 9,
			"x": 0,
			"y": 18,
			"w": 5
		},
		"1": {
			"h": 9,
			"x": 6,
			"y": 18,
			"w": 2
		},
		"2": {
			"h": 9,
			"x": 9,
			"y": 18,
			"w": 5
		},
		"3": {
			"h": 9,
			"x": 15,
			"y": 18,
			"w": 5
		},
		"4": {
			"h": 9,
			"x": 21,
			"y": 18,
			"w": 5
		},
		"5": {
			"h": 9,
			"x": 27,
			"y": 18,
			"w": 5
		},
		"6": {
			"h": 9,
			"x": 33,
			"y": 18,
			"w": 5
		},
		"7": {
			"h": 9,
			"x": 39,
			"y": 18,
			"w": 5
		},
		"8": {
			"h": 9,
			"x": 45,
			"y": 18,
			"w": 5
		},
		"9": {
			"h": 9,
			"x": 51,
			"y": 18,
			"w": 5
		},
		"#": {
			"h": 9,
			"x": 158,
			"y": 18,
			"w": 6
		},
		"l": {
			"h": 9,
			"x": 57,
			"y": 0,
			"w": 1
		},
		"\\\\/": {
			"h": 9,
			"x": 135,
			"y": 18,
			"w": 7
		},
		"b": {
			"h": 9,
			"x": 6,
			"y": 0,
			"w": 5
		},
		"-": {
			"h": 9,
			"x": 154,
			"y": 0,
			"w": 4
		},
		"U": {
			"h": 9,
			"x": 119,
			"y": 9,
			"w": 5
		},
		"[": {
			"h": 9,
			"x": 101,
			"y": 18,
			"w": 3
		},
		"Q": {
			"h": 9,
			"x": 95,
			"y": 9,
			"w": 5
		},
		"_": {
			"h": 9,
			"x": 164,
			"y": 9,
			"w": 6
		},
		"h": {
			"h": 9,
			"x": 41,
			"y": 0,
			"w": 5
		},
		"'": {
			"h": 9,
			"x": 69,
			"y": 18,
			"w": 1
		},
		")": {
			"h": 9,
			"x": 97,
			"y": 18,
			"w": 3
		},
		"f": {
			"h": 9,
			"x": 30,
			"y": 0,
			"w": 4
		},
		"Y": {
			"h": 9,
			"x": 145,
			"y": 9,
			"w": 5
		},
		"W": {
			"h": 9,
			"x": 131,
			"y": 9,
			"w": 7
		},
		"`": {
			"h": 9,
			"x": 161,
			"y": 9,
			"w": 2
		},
		"!": {
			"h": 9,
			"x": 57,
			"y": 18,
			"w": 1
		},
		"n": {
			"h": 9,
			"x": 67,
			"y": 0,
			"w": 5
		},
		"+": {
			"h": 9,
			"x": 148,
			"y": 0,
			"w": 5
		},
		"d": {
			"h": 9,
			"x": 18,
			"y": 0,
			"w": 5
		},
		"j": {
			"h": 9,
			"x": 49,
			"y": 0,
			"w": 2
		},
		"%": {
			"h": 9,
			"x": 150,
			"y": 18,
			"w": 7
		},
		"]": {
			"h": 9,
			"x": 105,
			"y": 18,
			"w": 3
		},
		"S": {
			"h": 9,
			"x": 107,
			"y": 9,
			"w": 5
		},
		"G": {
			"h": 9,
			"x": 36,
			"y": 9,
			"w": 5
		},
		"I": {
			"h": 9,
			"x": 48,
			"y": 9,
			"w": 3
		},
		"~": {
			"h": 9,
			"x": 171,
			"y": 9,
			"w": 5
		},
		"p": {
			"h": 9,
			"x": 79,
			"y": 0,
			"w": 5
		},
		"?": {
			"h": 9,
			"x": 59,
			"y": 18,
			"w": 5
		},
		"z": {
			"h": 9,
			"x": 139,
			"y": 0,
			"w": 5
		},
		";": {
			"h": 9,
			"x": 80,
			"y": 18,
			"w": 2
		},
		"t": {
			"h": 9,
			"x": 102,
			"y": 0,
			"w": 4
		},
		"C": {
			"h": 9,
			"x": 12,
			"y": 9,
			"w": 5
		},
		"M": {
			"h": 9,
			"x": 70,
			"y": 9,
			"w": 6
		},
		"r": {
			"h": 9,
			"x": 91,
			"y": 0,
			"w": 4
		},
		"=": {
			"h": 9,
			"x": 165,
			"y": 0,
			"w": 5
		},
		"|": {
			"h": 9,
			"x": 171,
			"y": 0,
			"w": 7
		},
		"K": {
			"h": 9,
			"x": 58,
			"y": 9,
			"w": 5
		},
		"E": {
			"h": 9,
			"x": 24,
			"y": 9,
			"w": 5
		},
		"O": {
			"h": 9,
			"x": 83,
			"y": 9,
			"w": 5
		},
		"A": {
			"h": 9,
			"x": 0,
			"y": 9,
			"w": 5
		},
		"v": {
			"h": 9,
			"x": 113,
			"y": 0,
			"w": 5
		},
		"x": {
			"h": 9,
			"x": 127,
			"y": 0,
			"w": 5
		},
		"^": {
			"h": 9,
			"x": 157,
			"y": 9,
			"w": 3
		},
		"P": {
			"h": 9,
			"x": 89,
			"y": 9,
			"w": 5
		},
		"(": {
			"h": 9,
			"x": 93,
			"y": 18,
			"w": 3
		},
		"g": {
			"h": 9,
			"x": 35,
			"y": 0,
			"w": 5
		},
		"i": {
			"h": 9,
			"x": 47,
			"y": 0,
			"w": 1
		},
		"&": {
			"h": 9,
			"x": 143,
			"y": 18,
			"w": 6
		},
		"c": {
			"h": 9,
			"x": 12,
			"y": 0,
			"w": 5
		},
		",": {
			"h": 9,
			"x": 74,
			"y": 18,
			"w": 2
		},
		"\"": {
			"h": 9,
			"x": 65,
			"y": 18,
			"w": 3
		},
		"m": {
			"h": 9,
			"x": 59,
			"y": 0,
			"w": 7
		},
		"Z": {
			"h": 9,
			"x": 151,
			"y": 9,
			"w": 5
		},
		"T": {
			"h": 9,
			"x": 113,
			"y": 9,
			"w": 5
		},
		"k": {
			"h": 9,
			"x": 52,
			"y": 0,
			"w": 4
		},
		"$": {
			"h": 9,
			"x": 165,
			"y": 18,
			"w": 7
		},
		"*": {
			"h": 9,
			"x": 159,
			"y": 0,
			"w": 5
		},
		"e": {
			"h": 9,
			"x": 24,
			"y": 0,
			"w": 5
		},
		"R": {
			"h": 9,
			"x": 101,
			"y": 9,
			"w": 5
		},
		"\\": {
			"h": 9,
			"x": 127,
			"y": 18,
			"w": 7
		},
		"V": {
			"h": 9,
			"x": 125,
			"y": 9,
			"w": 5
		},
		"X": {
			"h": 9,
			"x": 139,
			"y": 9,
			"w": 5
		},
		" ": {
			"h": 9,
			"x": 173,
			"y": 18,
			"w": 4
		},
		"o": {
			"h": 9,
			"x": 73,
			"y": 0,
			"w": 5
		},
		"a": {
			"h": 9,
			"x": 0,
			"y": 0,
			"w": 5
		},
		".": {
			"h": 9,
			"x": 71,
			"y": 18,
			"w": 2
		},
		":": {
			"h": 9,
			"x": 77,
			"y": 18,
			"w": 2
		},
		"u": {
			"h": 9,
			"x": 107,
			"y": 0,
			"w": 5
		},
		"{": {
			"h": 9,
			"x": 109,
			"y": 18,
			"w": 4
		},
		"L": {
			"h": 9,
			"x": 64,
			"y": 9,
			"w": 5
		},
		"B": {
			"h": 9,
			"x": 6,
			"y": 9,
			"w": 5
		},
		"H": {
			"h": 9,
			"x": 42,
			"y": 9,
			"w": 5
		},
		"F": {
			"h": 9,
			"x": 30,
			"y": 9,
			"w": 5
		},
		"q": {
			"h": 9,
			"x": 85,
			"y": 0,
			"w": 5
		},
		">": {
			"h": 9,
			"x": 88,
			"y": 18,
			"w": 4
		},
		"@": {
			"h": 9,
			"x": 119,
			"y": 18,
			"w": 7
		},
		"N": {
			"h": 9,
			"x": 77,
			"y": 9,
			"w": 5
		},
		"y": {
			"h": 9,
			"x": 133,
			"y": 0,
			"w": 5
		},
		"w": {
			"h": 9,
			"x": 119,
			"y": 0,
			"w": 7
		},
		"}": {
			"h": 9,
			"x": 114,
			"y": 18,
			"w": 4
		},
		"s": {
			"h": 9,
			"x": 96,
			"y": 0,
			"w": 5
		},
		"<": {
			"h": 9,
			"x": 83,
			"y": 18,
			"w": 4
		},
		"D": {
			"h": 9,
			"x": 18,
			"y": 9,
			"w": 5
		},
		"J": {
			"h": 9,
			"x": 52,
			"y": 9,
			"w": 5
		}
	}

}
